ease_tts/__init__.py
ease_tts/_tts.py
ease_tts-3.1.0.dist-info/licenses/LICENSE
ease_tts-3.1.0.dist-info/METADATA
ease_tts-3.1.0.dist-info/WHEEL
ease_tts-3.1.0.dist-info/top_level.txt
ease_tts-3.1.0.dist-info/RECORD
