Metadata-Version: 2.4
Name: ease-tts
Version: 3.1.0
Summary: Lightweight Python module for converting text into natural-sounding speech on Windows, macOS and Linux.
Author: Madhav
License: MIT
Project-URL: Homepage, https://github.com/Madhav703/ease-tts
Requires-Python: >=3.7
License-File: LICENSE
Requires-Dist: gTTS>=2.0
Requires-Dist: playsound>=1.3.0
Dynamic: license-file
